{
  "project_info": {
    "project_number": "956956313959",
    "project_id": "floran-chatty",
    "storage_bucket": "floran-chatty.appspot.com"
  },
  "client": [
    {
      "client_info": {
        "mobilesdk_app_id": "1:956956313959:android:e12325920a5427bc6607c2",
        "android_client_info": {
          "package_name": "com.example.floran_chatty"
        }
      },
      "oauth_client": [
        {
          "client_id": "956956313959-0kcbl8m4rlf9ao3c9dcuvqkhpf5b6jta.apps.googleusercontent.com",
          "client_type": 3
        }
      ],
      "api_key": [
        {
          "current_key": "AIzaSyDCanRQfHwYfjdnz0hrJ36pt4Bviz0HoDQ"
        }
      ],
      "services": {
        "appinvite_service": {
          "other_platform_oauth_client": [
            {
              "client_id": "956956313959-0kcbl8m4rlf9ao3c9dcuvqkhpf5b6jta.apps.googleusercontent.com",
              "client_type": 3
            }
          ]
        }
      }
    }
  ],
  "configuration_version": "1"
}